rusty_axe/__init__.py
rusty_axe/cluster_summary_template_js.html
rusty_axe/lumberjack.py
rusty_axe/node.py
rusty_axe/node_cluster.py
rusty_axe/prediction.py
rusty_axe/sample_cluster.py
rusty_axe/tree.py
rusty_axe/tree_reader.py
rusty_axe/tree_template.html
rusty_axe/utils.py
rusty_axe/visualization.py
rusty_axe/bin/rf_5
rusty_axe/html/tmp
rusty_axe/src/argminmax.rs
rusty_axe/src/fast_nipal_vector.rs
rusty_axe/src/hash_rv.rs
rusty_axe/src/io.rs
rusty_axe/src/main.rs
rusty_axe/src/node.rs
rusty_axe/src/random_forest.rs
rusty_axe/src/randutils.rs
rusty_axe/src/rank_matrix.rs
rusty_axe/src/rank_vector.rs
rusty_axe/src/utils.rs
rusty_axe_bbrener1-0.68.dist-info/METADATA
rusty_axe_bbrener1-0.68.dist-info/WHEEL
rusty_axe_bbrener1-0.68.dist-info/top_level.txt
rusty_axe_bbrener1-0.68.dist-info/RECORD
