Metadata-Version: 2.1
Name: rusty-axe-bbrener1
Version: 0.68
Summary: Random Forest Latent Structure (Biology)
Home-page: https://github.com/bbrener1/rf_5
Author: Boris Brenerman
Author-email: bbrener1@jhu.edu
License: UNKNOWN
Project-URL: Bug Tracker, https://github.com/bbrener1/rf_5/issues
Platform: UNKNOWN
Classifier: Programming Language :: Python :: 3
Classifier: License :: OSI Approved :: MIT License
Classifier: Operating System :: MacOS :: MacOS X
Classifier: Operating System :: POSIX
Classifier: Programming Language :: Rust
Classifier: Topic :: Scientific/Engineering :: Bio-Informatics
Requires-Dist: umap-learn
Requires-Dist: leidenalg
Requires-Dist: scikit-learn
Requires-Dist: matplotlib (>=3.4.2)
